{
  "schemes": [
    {
      "name": "Everforest",

      "cursorColor": "#EEEEEE",
      "selectionBackground": "#637E73",

      "background": "#2D353B",
      "foreground": "#FDF6D3",

      "black": "#4F5B58",
      "blue": "#C3D3FB",
      "cyan": "#BAFCF2",
      "green": "#C3E5A5",
      "purple": "#F6CDF6",
      "red": "#F2A9A8",
      "white": "#F2EFDF",
      "yellow": "#FEFCBC",

      "brightBlack": "#5D6B66",
      "brightBlue": "#C3D3FB",
      "brightCyan": "#BAFCF2",
      "brightGreen": "#C3E5A5",
      "brightPurple": "#F6CDF6",
      "brightRed": "#F2A9A8",
      "brightWhite": "#FFFBEF",
      "brightYellow": "#FEFCBC"
    }
  ]
}
